aws_embedded_metrics/__init__.py
aws_embedded_metrics/constants.py
aws_embedded_metrics/exceptions.py
aws_embedded_metrics/py.typed
aws_embedded_metrics/storage_resolution.py
aws_embedded_metrics/unit.py
aws_embedded_metrics/utils.py
aws_embedded_metrics/validator.py
aws_embedded_metrics/config/__init__.py
aws_embedded_metrics/config/configuration.py
aws_embedded_metrics/config/environment_configuration_provider.py
aws_embedded_metrics/environment/__init__.py
aws_embedded_metrics/environment/default_environment.py
aws_embedded_metrics/environment/ec2_environment.py
aws_embedded_metrics/environment/environment_detector.py
aws_embedded_metrics/environment/lambda_environment.py
aws_embedded_metrics/environment/local_environment.py
aws_embedded_metrics/logger/__init__.py
aws_embedded_metrics/logger/metric.py
aws_embedded_metrics/logger/metrics_context.py
aws_embedded_metrics/logger/metrics_logger.py
aws_embedded_metrics/logger/metrics_logger_factory.py
aws_embedded_metrics/metric_scope/__init__.py
aws_embedded_metrics/serializers/__init__.py
aws_embedded_metrics/serializers/log_serializer.py
aws_embedded_metrics/sinks/__init__.py
aws_embedded_metrics/sinks/agent_sink.py
aws_embedded_metrics/sinks/stdout_sink.py
aws_embedded_metrics/sinks/tcp_client.py
aws_embedded_metrics/sinks/udp_client.py
aws_embedded_metrics-3.3.0.dist-info/LICENSE
aws_embedded_metrics-3.3.0.dist-info/METADATA
aws_embedded_metrics-3.3.0.dist-info/NOTICE
aws_embedded_metrics-3.3.0.dist-info/WHEEL
aws_embedded_metrics-3.3.0.dist-info/top_level.txt
aws_embedded_metrics-3.3.0.dist-info/RECORD
