Metadata-Version: 2.1
Name: aws-embedded-metrics
Version: 3.3.0
Summary: AWS Embedded Metrics Package
Home-page: https://github.com/awslabs/aws-embedded-metrics-python
Author: Amazon Web Services
Author-email: jarnance@amazon.com
License: UNKNOWN
Keywords: aws logs metrics emf
Platform: UNKNOWN
Classifier: Programming Language :: Python :: 3
Classifier: Operating System :: OS Independent
Classifier: Development Status :: 5 - Production/Stable
Classifier: Intended Audience :: Developers
Classifier: Natural Language :: English
Classifier: License :: OSI Approved :: Apache Software License
Requires-Python: >=3.6
License-File: LICENSE
License-File: NOTICE
Requires-Dist: aiohttp
